google/cloud/pubsublite/__init__.py
google/cloud/pubsublite/admin_client.py
google/cloud/pubsublite/admin_client_interface.py
google/cloud/pubsublite/gapic_version.py
google/cloud/pubsublite/py.typed
google/cloud/pubsublite/cloudpubsub/__init__.py
google/cloud/pubsublite/cloudpubsub/message_transformer.py
google/cloud/pubsublite/cloudpubsub/message_transforms.py
google/cloud/pubsublite/cloudpubsub/nack_handler.py
google/cloud/pubsublite/cloudpubsub/publisher_client.py
google/cloud/pubsublite/cloudpubsub/publisher_client_interface.py
google/cloud/pubsublite/cloudpubsub/reassignment_handler.py
google/cloud/pubsublite/cloudpubsub/subscriber_client.py
google/cloud/pubsublite/cloudpubsub/subscriber_client_interface.py
google/cloud/pubsublite/cloudpubsub/internal/__init__.py
google/cloud/pubsublite/cloudpubsub/internal/ack_set_tracker.py
google/cloud/pubsublite/cloudpubsub/internal/ack_set_tracker_impl.py
google/cloud/pubsublite/cloudpubsub/internal/assigning_subscriber.py
google/cloud/pubsublite/cloudpubsub/internal/async_publisher_impl.py
google/cloud/pubsublite/cloudpubsub/internal/client_multiplexer.py
google/cloud/pubsublite/cloudpubsub/internal/make_publisher.py
google/cloud/pubsublite/cloudpubsub/internal/make_subscriber.py
google/cloud/pubsublite/cloudpubsub/internal/managed_event_loop.py
google/cloud/pubsublite/cloudpubsub/internal/multiplexed_async_publisher_client.py
google/cloud/pubsublite/cloudpubsub/internal/multiplexed_async_subscriber_client.py
google/cloud/pubsublite/cloudpubsub/internal/multiplexed_publisher_client.py
google/cloud/pubsublite/cloudpubsub/internal/multiplexed_subscriber_client.py
google/cloud/pubsublite/cloudpubsub/internal/publisher_impl.py
google/cloud/pubsublite/cloudpubsub/internal/single_partition_subscriber.py
google/cloud/pubsublite/cloudpubsub/internal/single_publisher.py
google/cloud/pubsublite/cloudpubsub/internal/single_subscriber.py
google/cloud/pubsublite/cloudpubsub/internal/sorted_list.py
google_cloud_pubsublite-1.11.1.dist-info/LICENSE
google_cloud_pubsublite-1.11.1.dist-info/METADATA
google_cloud_pubsublite-1.11.1.dist-info/WHEEL
google_cloud_pubsublite-1.11.1.dist-info/top_level.txt
google_cloud_pubsublite-1.11.1.dist-info/RECORD
