Metadata-Version: 2.1
Name: google-cloud-pubsublite
Version: 1.11.1
Summary: Google Cloud Pubsublite API client library
Home-page: https://github.com/googleapis/python-pubsublite
Author: Google LLC
Author-email: googleapis-packages@google.com
License: Apache 2.0
Platform: Posix; MacOS X; Windows
Classifier: Development Status :: 5 - Production/Stable
Classifier: Intended Audience :: Developers
Classifier: License :: OSI Approved :: Apache Software License
Classifier: Programming Language :: Python
Classifier: Programming Language :: Python :: 3
Classifier: Programming Language :: Python :: 3.8
Classifier: Programming Language :: Python :: 3.9
Classifier: Programming Language :: Python :: 3.10
Classifier: Programming Language :: Python :: 3.11
Classifier: Programming Language :: Python :: 3.12
Classifier: Operating System :: OS Independent
Classifier: Topic :: Internet
Requires-Python: >=3.8
License-File: LICENSE
Requires-Dist: google-cloud-pubsub<3.0.0dev,>=2.10.0
Requires-Dist: grpcio<2.0.0dev,>=1.38.1
Requires-Dist: grpcio-status<2.0.0dev,>=1.38.1
Requires-Dist: overrides<8.0.0,>=6.0.1
Requires-Dist: overrides<8.0.0,>=7.0.1; python_version >= "3.12"
Requires-Dist: google-api-core[grpc]!=2.0.*,!=2.1.*,!=2.2.*,!=2.3.*,!=2.4.*,!=2.5.*,!=2.6.*,!=2.7.*,<3.0.0dev,>=1.33.2
